#桥接方法

桥接方法是 JDK 1.5 引入泛型后，为了使Java的泛型方法生成的字节码和 1.5 版本前的字节码相兼容，由编译器自动生成的方法。

##举个例子

```java
public interface SupClass<T>{
    public void method(T t);
}

public class SubClass implements SupClass<String>{
    public void method(String s){
        System.out.println(s);
    };
}

```

上面这份代码进行了使用了泛型，要求类型是String。

用javap查看编译的字节码文件：

```java
javap test\SubClass.class
Compiled from "SubClass.java"
public class test.SubClass implements test.SupClass<java.lang.String> {
  public test.SubClass();
  public void method(java.lang.String);
  public void method(java.lang.Object);
}

javap -c test\SubClass.class
Compiled from "SubClass.java"
public class test.SubClass implements test.SupClass<java.lang.String> {
  public test.SubClass();
    Code:
       0: aload_0
       1: invokespecial #1                  // Method java/lang/Object."<init>":()V
       4: return

  public void method(java.lang.String);
    Code:
       0: getstatic     #2                  // Field java/lang/System.out:Ljava/io/PrintStream;
       3: aload_1
       4: invokevirtual #3                  // Method java/io/PrintStream.println:(Ljava/lang/String;)V
       7: return

  public void method(java.lang.Object);
    Code:
       0: aload_0
       1: aload_1
       2: checkcast     #4                  // class java/lang/String
       5: invokevirtual #5                  // Method method:(Ljava/lang/String;)V
       8: return
}
```

可以看到多了一个方法`public void method(java.lang.Object);`

这个方法做了三件事情：
1.将得到的Object参数强制转换为String

2.调用method(String s)这个方法

3.return

所以这个方法相当于

```java
public void method(Object o){
    String s = (String)o;
    this.method(s);
    return ;
}
```

这就是桥接方法



## 为什么要用桥接方法

因为泛型是在1.5引入的，为了向前兼容，所以会在编译时去掉泛型（泛型擦除），由于java泛型的擦除特性，如果不生成桥接方法，那么与1.5之前的字节码就不兼容了。



## 泛型的好处

我们希望在编译的之后就知道类型转换的问题，而不是在运行的时候才发现类型不能转换，而报错。

比如下面的代码使用了泛型的话：

```java
import java.util.ArrayList;
public class Test{

	public void main(){
		ArrayList<String> list = new ArrayList<>();
		list.add(new Test());
				
	}
}
```

我们编译的时候会直接报错：

```java
javac test/Test.java
test\Test.java:6: 错误: 对于add(Test), 找不到合适的方法
                list.add(new Test());
                    ^
    方法 Collection.add(String)不适用
      (参数不匹配; Test无法转换为String)
    方法 List.add(String)不适用
      (参数不匹配; Test无法转换为String)
    方法 AbstractCollection.add(String)不适用
      (参数不匹配; Test无法转换为String)
    方法 AbstractList.add(String)不适用
      (参数不匹配; Test无法转换为String)
    方法 ArrayList.add(String)不适用
      (参数不匹配; Test无法转换为String)
```

